.gitignore
.travis.yml
LICENSE
README.rst
contributors.txt
setup.py
benchpress/__init__.py
benchpress/argument_handling.py
benchpress/benchpress.py
benchpress/info.py
benchpress/run.py
benchpress/suite_schema.json
benchpress/suite_util.py
benchpress/testing.py
benchpress/time_util.py
benchpress.egg-info/PKG-INFO
benchpress.egg-info/SOURCES.txt
benchpress.egg-info/dependency_links.txt
benchpress.egg-info/entry_points.txt
benchpress.egg-info/requires.txt
benchpress.egg-info/top_level.txt
benchpress/benchmarks/__init__.py
benchpress/benchmarks/util.py
benchpress/benchmarks/_utils/c99/Makefile.common
benchpress/benchmarks/_utils/c99/include/bp_util.h
benchpress/benchmarks/_utils/c99/include/Random123/MicroURNG.hpp
benchpress/benchmarks/_utils/c99/include/Random123/ReinterpretCtr.hpp
benchpress/benchmarks/_utils/c99/include/Random123/aes.h
benchpress/benchmarks/_utils/c99/include/Random123/array.h
benchpress/benchmarks/_utils/c99/include/Random123/ars.h
benchpress/benchmarks/_utils/c99/include/Random123/gsl_microrng.h
benchpress/benchmarks/_utils/c99/include/Random123/philox.h
benchpress/benchmarks/_utils/c99/include/Random123/threefry.h
benchpress/benchmarks/_utils/c99/include/Random123/conventional/Engine.hpp
benchpress/benchmarks/_utils/c99/include/Random123/conventional/gsl_cbrng.h
benchpress/benchmarks/_utils/c99/include/Random123/features/clangfeatures.h
benchpress/benchmarks/_utils/c99/include/Random123/features/compilerfeatures.h
benchpress/benchmarks/_utils/c99/include/Random123/features/gccfeatures.h
benchpress/benchmarks/_utils/c99/include/Random123/features/iccfeatures.h
benchpress/benchmarks/_utils/c99/include/Random123/features/msvcfeatures.h
benchpress/benchmarks/_utils/c99/include/Random123/features/nvccfeatures.h
benchpress/benchmarks/_utils/c99/include/Random123/features/open64features.h
benchpress/benchmarks/_utils/c99/include/Random123/features/openclfeatures.h
benchpress/benchmarks/_utils/c99/include/Random123/features/pgccfeatures.h
benchpress/benchmarks/_utils/c99/include/Random123/features/sse.h
benchpress/benchmarks/_utils/c99/include/Random123/features/sunprofeatures.h
benchpress/benchmarks/_utils/c99/include/Random123/features/xlcfeatures.h
