Metadata-Version: 1.1
Name: benchpress
Version: 3.0.5.post18
Summary: Benchmark suite tool
Home-page: http://benchpress.readthedocs.io
Author: Mads R. B. Kristensen
Author-email: madsbk@gmail.com
License: GPL
Keywords: Benchmark,Bohrium,bh107
Platform: Linux
Platform: OSX
Classifier: Development Status :: 4 - Beta
Classifier: Intended Audience :: End Users/Desktop
Classifier: Topic :: Multimedia
Classifier: License :: OSI Approved :: GNU General Public License (GPL)
Classifier: Programming Language :: Python :: 2.7
Classifier: Programming Language :: Python :: 3
